[
  {
    "id": 8,
    "name": "17-LL",
    "type": "IntensiveCare",
    "floor": 4,
    "description": "Intenzivna nega standardno",
    "staticEquipment": [
      {
        "roomName": "17-LL",
        "id": 1,
        "name": "laseri",
        "quantity": 15
      },
      {
        "roomName": "17-LL",
        "id": 2,
        "name": "stolice",
        "quantity": 44
      }
    ]
  },
  {
    "id": 9,
    "name": "80-TRA",
    "type": "Ordination",
    "floor": 1,
    "description": "Ordinacija za ljude srednjih godina",
    "staticEquipment": [
      {
        "roomName": "80-TRA",
        "id": 13332,
        "name": "skeneri",
        "quantity": 15
      },
      {
        "roomName": "80-TRA",
        "id": 13333,
        "name": "lasers",
        "quantity": 2
      }
    ]
  },
  {
    "id": 10,
    "name": "8-GT",
    "type": "Ordination",
    "floor": 2,
    "description": "Obavlja se svakodnevni pregled",
    "staticEquipment": []
  },
  {
    "id": 11,
    "name": "GB-44",
    "type": "Ordination",
    "floor": 3,
    "description": "Soba koja sluzi za pokazivanje staticke opreme",
    "staticEquipment": [
      {
        "roomName": "GB-44",
        "id": 1,
        "name": "stolice",
        "quantity": 500
      },
      {
        "roomName": "GB-44",
        "id": 19,
        "name": "ormari",
        "quantity": 400
      },
      {
        "roomName": "GB-44",
        "id": 112,
        "name": "skeneri",
        "quantity": 54
      }
    ]
  },
  {
    "id": 12,
    "name": "105-FR",
    "type": "Ordination",
    "floor": 2,
    "description": "Soba koja sluzi za pokazivanje staticke opreme",
    "staticEquipment": [
      {
        "roomName": "105-FR",
        "id": 22,
        "name": "stolovi",
        "quantity": 40
      },
      {
        "roomName": "105-FR",
        "id": 5,
        "name": "klupe",
        "quantity": 170
      },
      {
        "roomName": "105-FR",
        "id": 15,
        "name": "aparati",
        "quantity": 4
      },
      {
        "roomName": "105-FR",
        "id": 3,
        "name": "solarni",
        "quantity": 3
      },
      {
        "roomName": "105-FR",
        "id": 1,
        "name": "stolice",
        "quantity": 500
      },
      {
        "roomName": "105-FR",
        "id": 19,
        "name": "ormari",
        "quantity": 350
      },
      {
        "roomName": "105-FR",
        "id": 112,
        "name": "skeneri",
        "quantity": 435
      }
    ]
  },
  {
    "id": 4141,
    "name": "140-NOVA",
    "type": "IntensiveCare",
    "floor": 3,
    "description": "fwefwh",
    "staticEquipment": [
      {
        "roomName": "140-NOVA",
        "id": 284,
        "name": "tables",
        "quantity": 8
      },
      {
        "roomName": "140-NOVA",
        "id": 843,
        "name": "lockers",
        "quantity": 2
      },
      {
        "roomName": "140-NOVA",
        "id": 914,
        "name": "respirators",
        "quantity": 5
      },
      {
        "roomName": "140-NOVA",
        "id": 883,
        "name": "lasers",
        "quantity": 3
      },
      {
        "roomName": "140-NOVA",
        "id": 313,
        "name": "lockers",
        "quantity": 3
      }
    ]
  },
  {
    "id": 4991,
    "name": "33-LG",
    "type": "IntensiveCare",
    "floor": 4,
    "description": "fwefwg",
    "staticEquipment": [
      {
        "roomName": "33-LG",
        "id": 12127,
        "name": "benches",
        "quantity": 3
      },
      {
        "roomName": "33-LG",
        "id": 11920,
        "name": "chairs",
        "quantity": 20
      },
      {
        "roomName": "33-LG",
        "id": 12408,
        "name": "lockers",
        "quantity": 2
      },
      {
        "roomName": "33-LG",
        "id": 12415,
        "name": "respirators",
        "quantity": 2
      }
    ]
  },
  {
    "id": 4927,
    "name": "104-YO",
    "type": "IntensiveCare",
    "floor": 4,
    "description": "fwefwg",
    "staticEquipment": [
      {
        "roomName": "104-YO",
        "id": 11690,
        "name": "lasers",
        "quantity": 8
      },
      {
        "roomName": "104-YO",
        "id": 12414,
        "name": "respirators",
        "quantity": 4
      },
      {
        "roomName": "104-YO",
        "id": 11912,
        "name": "chairs",
        "quantity": 2
      }
    ]
  },
  {
    "id": 5100,
    "name": "801-RT",
    "type": "IntensiveCare",
    "floor": 1,
    "description": "gerghe",
    "staticEquipment": [
      {
        "roomName": "801-RT",
        "id": 12675,
        "name": "benches",
        "quantity": 3
      },
      {
        "roomName": "801-RT",
        "id": 13312,
        "name": "chairs",
        "quantity": 2
      },
      {
        "roomName": "801-RT",
        "id": 12531,
        "name": "lasers",
        "quantity": 10
      }
    ]
  },
  {
    "id": 5073,
    "name": "101-YU",
    "type": "OperatingRoom",
    "floor": 1,
    "description": "vwervb",
    "staticEquipment": [
      {
        "roomName": "101-YU",
        "id": 13331,
        "name": "respirators",
        "quantity": 7
      },
      {
        "roomName": "101-YU",
        "id": 12848,
        "name": "pump",
        "quantity": 3
      },
      {
        "roomName": "101-YU",
        "id": 13315,
        "name": "chairs",
        "quantity": 12
      }
    ]
  },
  {
    "id": 5101,
    "name": "aaa4-YU",
    "type": "OperatingRoom",
    "floor": 1,
    "description": "vwervb",
    "staticEquipment": []
  }
]